proxmoxmanager/__init__.py
proxmoxmanager/main.py
proxmoxmanager/utils/__init__.py
proxmoxmanager/utils/api.py
proxmoxmanager/utils/decorators.py
proxmoxmanager/utils/classes/__init__.py
proxmoxmanager/utils/classes/containers.py
proxmoxmanager/utils/classes/errors.py
proxmoxmanager/utils/classes/nodes.py
proxmoxmanager/utils/classes/users.py
proxmoxmanager/utils/classes/vms.py
tests/__init__.py
tests/test_containers.py
tests/test_decorators.py
tests/test_nodes.py
tests/test_proxmoxmanager.py
tests/test_users.py
tests/test_vms.py
proxmoxmanager-1.0.4.dist-info/LICENSE
proxmoxmanager-1.0.4.dist-info/METADATA
proxmoxmanager-1.0.4.dist-info/WHEEL
proxmoxmanager-1.0.4.dist-info/top_level.txt
proxmoxmanager-1.0.4.dist-info/RECORD
