Metadata-Version: 2.1
Name: proxmoxmanager
Version: 1.0.4
Summary: Smart Proxmox VE API wrapper for managing resources automatically
Home-page: https://github.com/igorlitvak/proxmoxmanager
Author: Igor Litvak, ITMO University
License: UNKNOWN
Platform: UNKNOWN
Classifier: Development Status :: 4 - Beta
Classifier: License :: OSI Approved :: MIT License
Classifier: Programming Language :: Python :: 3
Classifier: Programming Language :: Python :: 3.7
Classifier: Programming Language :: Python :: 3.8
Classifier: Programming Language :: Python :: 3.9
Classifier: Programming Language :: Python :: 3.10
Requires-Python: >=3.7, <4
License-File: LICENSE
Requires-Dist: proxmoxer
Requires-Dist: requests
